<?xml version="1.0"?>
<notion label="Notion par defaut">           <titre>titre par defaut</titre>           <contenu>             <texte>Un cours comporte id&#xE9;alement trois diff&#xE9;rents niveaux d&#x2019;information hi&#xE9;rarchis&#xE9;s et num&#xE9;rot&#xE9;s en pseudo-d&#xE9;cimales (Ex. : 2, 2.1, 2.1.1) (Voir Annexe).</texte>             <texte>Les titres et sous titres doivent &#xEA;tres bien enchain&#xE9;s. On doit retrouver toute les imbrications d&#x2019;un sous titre dans sa num&#xE9;rotation. Par exemple, apr&#xE8;s le titre 1.1, au lieu d&#x2019;annoncer le titre a) on doit &#xE9;crire 1.1.a. On doit s&#x2019;assurer que chaque titre est reconnu comme tel par Word si nom, le titre sera consid&#xE9;rer comme un texte simple.</texte>           </contenu>         </notion>
